[
    {
        "featured_products": null,
        "isdeleted": false,
        "is_offer": null,
        "show_stock": true,
        "status": null,
        "top_selling": true,
        "trending_products": null,
        "discount": null,
        "duration": null,
        "expiry": null,
        "offered_price": 999,
        "price": 700,
        "quantity": null,
        "selling_price": 1049,
        "stocks": 5,
        "attributes": null,
        "images": [
            "https://d246wdlhxeb44j.cloudfront.net/1741871852536-cropped-1741871852525.png"
        ],
        "alpha_numeric": null,
        "bar_code": null,
        "description": "<ul><li>copper  silk</li><li>border saree</li></ul>",
        "image": null,
        "name": "soft silk",
        "product_code": null,
        "videos": null,
        "created_at": "2025-03-13T13:17:43.921582",
        "updated_at": "2025-03-19T18:07:03.534617",
        "category": "8b6adf7c-f5fe-4473-b927-c90253d5f4cc",
        "id": "9995ee68-eb4c-485f-8927-760e150b3997",
        "shop_id": "c0554ffb-8e3a-4ce4-bb3b-d345873e061a",
        "sub_category": "af8e85d8-3909-45fe-81a2-d3fb95260093"
    },
    {
        "featured_products": null,
        "isdeleted": false,
        "is_offer": null,
        "show_stock": true,
        "status": null,
        "top_selling": true,
        "trending_products": null,
        "discount": null,
        "duration": null,
        "expiry": null,
        "offered_price": null,
        "price": 650,
        "quantity": null,
        "selling_price": 899,
        "stocks": 12,
        "attributes": null,
        "images": [
            "https://d246wdlhxeb44j.cloudfront.net/1741507026779-cropped-1741507026769.png"
        ],
        "alpha_numeric": null,
        "bar_code": null,
        "description": "<ul><li>dual colour</li><li>work blouse combo</li><li>blouse point 90</li></ul>",
        "image": null,
        "name": "neenga asai patta saree",
        "product_code": null,
        "videos": null,
        "created_at": null,
        "updated_at": "2025-03-21T07:22:06.503386",
        "category": "8b6adf7c-f5fe-4473-b927-c90253d5f4cc",
        "id": "a27ed749-a651-4d5e-882b-112fba249be6",
        "shop_id": "c0554ffb-8e3a-4ce4-bb3b-d345873e061a",
        "sub_category": "5be3bab2-73ff-43a9-af87-e398a563c974"
    },
    {
        "featured_products": null,
        "isdeleted": false,
        "is_offer": null,
        "show_stock": true,
        "status": null,
        "top_selling": true,
        "trending_products": null,
        "discount": null,
        "duration": null,
        "expiry": null,
        "offered_price": 999,
        "price": 700,
        "quantity": null,
        "selling_price": 1049,
        "stocks": 6,
        "attributes": null,
        "images": [
            "https://d246wdlhxeb44j.cloudfront.net/1741871777105-cropped-1741871777094.png"
        ],
        "alpha_numeric": null,
        "bar_code": null,
        "description": "<ul><li>copper silk</li><li>border saree</li></ul>",
        "image": null,
        "name": "soft silk",
        "product_code": null,
        "videos": null,
        "created_at": "2025-03-13T13:16:23.205473",
        "updated_at": "2025-03-20T03:15:55.354922",
        "category": "8b6adf7c-f5fe-4473-b927-c90253d5f4cc",
        "id": "561dc079-785a-49cc-9d89-f7383d012118",
        "shop_id": "c0554ffb-8e3a-4ce4-bb3b-d345873e061a",
        "sub_category": "af8e85d8-3909-45fe-81a2-d3fb95260093"
    },
    {
        "featured_products": null,
        "isdeleted": false,
        "is_offer": null,
        "show_stock": true,
        "status": null,
        "top_selling": null,
        "trending_products": true,
        "discount": null,
        "duration": null,
        "expiry": null,
        "offered_price": 349,
        "price": 260,
        "quantity": null,
        "selling_price": 399,
        "stocks": 8,
        "attributes": null,
        "images": [
            "https://d246wdlhxeb44j.cloudfront.net/1741508337091-cropped-1741508337076.png"
        ],
        "alpha_numeric": null,
        "bar_code": null,
        "description": "<ul><li>trending modal</li><li>work blouse</li><li>combo</li></ul>",
        "image": null,
        "name": "online",
        "product_code": null,
        "videos": null,
        "created_at": null,
        "updated_at": "2025-03-10T06:50:58.770317",
        "category": "8b6adf7c-f5fe-4473-b927-c90253d5f4cc",
        "id": "9f652880-f410-4460-ad80-bfffc0bf6e49",
        "shop_id": "c0554ffb-8e3a-4ce4-bb3b-d345873e061a",
        "sub_category": "5be3bab2-73ff-43a9-af87-e398a563c974"
    },
    {
        "featured_products": null,
        "isdeleted": false,
        "is_offer": null,
        "show_stock": true,
        "status": null,
        "top_selling": null,
        "trending_products": true,
        "discount": null,
        "duration": null,
        "expiry": null,
        "offered_price": 349,
        "price": 260,
        "quantity": null,
        "selling_price": 499,
        "stocks": 4,
        "attributes": null,
        "images": [
            "https://d246wdlhxeb44j.cloudfront.net/1741780732971-cropped-1741780732959.png"
        ],
        "alpha_numeric": null,
        "bar_code": null,
        "description": "<ul><li>summer special</li><li>cotton</li><li>offer</li></ul>",
        "image": null,
        "name": "cotton meganthi green",
        "product_code": null,
        "videos": null,
        "created_at": "2025-03-12T11:58:57.967988",
        "updated_at": "2025-03-18T07:14:55.726202",
        "category": "8b6adf7c-f5fe-4473-b927-c90253d5f4cc",
        "id": "6250400a-569f-42c6-ab76-d39e1da7c413",
        "shop_id": "c0554ffb-8e3a-4ce4-bb3b-d345873e061a",
        "sub_category": "ab0965b3-1db4-49f2-85f0-bbd5121dd1ef"
    },
    {
        "featured_products": null,
        "isdeleted": false,
        "is_offer": null,
        "show_stock": true,
        "status": null,
        "top_selling": null,
        "trending_products": true,
        "discount": null,
        "duration": null,
        "expiry": null,
        "offered_price": 450,
        "price": 330,
        "quantity": null,
        "selling_price": 499,
        "stocks": 3,
        "attributes": null,
        "images": [
            "https://d246wdlhxeb44j.cloudfront.net/1741509701907-cropped-1741509701890.png"
        ],
        "alpha_numeric": null,
        "bar_code": null,
        "description": "<ul><li>running blouse saress </li><li>braze</li></ul>",
        "image": null,
        "name": "braze",
        "product_code": null,
        "videos": null,
        "created_at": null,
        "updated_at": "2025-03-17T12:14:41.599042",
        "category": "8b6adf7c-f5fe-4473-b927-c90253d5f4cc",
        "id": "62f85a16-9c42-4ba9-b3d2-a84abe6c6860",
        "shop_id": "c0554ffb-8e3a-4ce4-bb3b-d345873e061a",
        "sub_category": "a16e3941-94f7-4899-a2cf-dbacafd77f78"
    },
    {
        "featured_products": null,
        "isdeleted": false,
        "is_offer": null,
        "show_stock": true,
        "status": null,
        "top_selling": null,
        "trending_products": true,
        "discount": null,
        "duration": null,
        "expiry": null,
        "offered_price": 349,
        "price": 260,
        "quantity": null,
        "selling_price": 499,
        "stocks": 2,
        "attributes": null,
        "images": [
            "https://d246wdlhxeb44j.cloudfront.net/1741780553236-cropped-1741780553224.png"
        ],
        "alpha_numeric": null,
        "bar_code": null,
        "description": "<ul><li>summer special</li><li>offer price</li><li>cotton</li></ul>",
        "image": null,
        "name": "cotton green",
        "product_code": null,
        "videos": null,
        "created_at": "2025-03-12T11:56:07.357189",
        "updated_at": "2025-03-25T11:27:39.738582",
        "category": "8b6adf7c-f5fe-4473-b927-c90253d5f4cc",
        "id": "d77b222d-150e-473a-8442-f28ba7f340ea",
        "shop_id": "c0554ffb-8e3a-4ce4-bb3b-d345873e061a",
        "sub_category": "ab0965b3-1db4-49f2-85f0-bbd5121dd1ef"
    },
    {
        "featured_products": null,
        "isdeleted": false,
        "is_offer": null,
        "show_stock": true,
        "status": null,
        "top_selling": true,
        "trending_products": null,
        "discount": null,
        "duration": null,
        "expiry": null,
        "offered_price": 999,
        "price": 700,
        "quantity": null,
        "selling_price": 1049,
        "stocks": 6,
        "attributes": null,
        "images": [
            "https://d246wdlhxeb44j.cloudfront.net/1741871937309-cropped-1741871937298.png"
        ],
        "alpha_numeric": null,
        "bar_code": null,
        "description": "<ul><li>copper silk</li><li>border saree</li></ul>",
        "image": null,
        "name": "soft silk",
        "product_code": null,
        "videos": null,
        "created_at": "2025-03-13T13:19:12.606552",
        "updated_at": "2025-03-18T08:39:59.214384",
        "category": "8b6adf7c-f5fe-4473-b927-c90253d5f4cc",
        "id": "22546f35-5036-440c-a39f-1217b6e747a2",
        "shop_id": "c0554ffb-8e3a-4ce4-bb3b-d345873e061a",
        "sub_category": "af8e85d8-3909-45fe-81a2-d3fb95260093"
    },
    {
        "featured_products": null,
        "isdeleted": false,
        "is_offer": null,
        "show_stock": true,
        "status": null,
        "top_selling": true,
        "trending_products": null,
        "discount": null,
        "duration": null,
        "expiry": null,
        "offered_price": 999,
        "price": 700,
        "quantity": null,
        "selling_price": 1049,
        "stocks": 4,
        "attributes": null,
        "images": [
            "https://d246wdlhxeb44j.cloudfront.net/1741871623956-cropped-1741871623944.png"
        ],
        "alpha_numeric": null,
        "bar_code": null,
        "description": "<ul><li>coffer soft silk</li><li>border saree</li></ul>",
        "image": null,
        "name": "soft silk",
        "product_code": null,
        "videos": null,
        "created_at": "2025-03-13T13:13:52.115649",
        "updated_at": "2025-03-17T06:53:31.37669",
        "category": "8b6adf7c-f5fe-4473-b927-c90253d5f4cc",
        "id": "e1c0ffb7-5740-4647-88b6-afd79a72f000",
        "shop_id": "c0554ffb-8e3a-4ce4-bb3b-d345873e061a",
        "sub_category": "af8e85d8-3909-45fe-81a2-d3fb95260093"
    },
    {
        "featured_products": null,
        "isdeleted": false,
        "is_offer": null,
        "show_stock": true,
        "status": null,
        "top_selling": null,
        "trending_products": true,
        "discount": null,
        "duration": null,
        "expiry": null,
        "offered_price": 349,
        "price": 260,
        "quantity": null,
        "selling_price": 499,
        "stocks": 7,
        "attributes": null,
        "images": [
            "https://d246wdlhxeb44j.cloudfront.net/1741780817436-cropped-1741780817425.png"
        ],
        "alpha_numeric": null,
        "bar_code": null,
        "description": "<ul><li>summer special</li><li>cotton</li><li>offer</li></ul>",
        "image": null,
        "name": "cotton light pink",
        "product_code": null,
        "videos": null,
        "created_at": "2025-03-12T12:00:23.391881",
        "updated_at": "2025-03-23T05:43:21.950169",
        "category": "8b6adf7c-f5fe-4473-b927-c90253d5f4cc",
        "id": "34bfc77c-86e6-48af-9b54-20476621adbd",
        "shop_id": "c0554ffb-8e3a-4ce4-bb3b-d345873e061a",
        "sub_category": "ab0965b3-1db4-49f2-85f0-bbd5121dd1ef"
    },
    {
        "featured_products": null,
        "isdeleted": false,
        "is_offer": null,
        "show_stock": true,
        "status": null,
        "top_selling": null,
        "trending_products": true,
        "discount": null,
        "duration": null,
        "expiry": null,
        "offered_price": null,
        "price": 350,
        "quantity": null,
        "selling_price": 499,
        "stocks": 4,
        "attributes": null,
        "images": [
            "https://d246wdlhxeb44j.cloudfront.net/1741508093289-cropped-1741508093284.png",
            "https://d246wdlhxeb44j.cloudfront.net/1741508146394-cropped-1741508146387.png"
        ],
        "alpha_numeric": null,
        "bar_code": null,
        "description": "<ul><li>Poonam saree</li><li>stone work</li><li>running blouse</li><li>super qulity</li></ul>",
        "image": null,
        "name": "susila pink",
        "product_code": null,
        "videos": null,
        "created_at": null,
        "updated_at": "2025-03-29T06:58:46.857783",
        "category": "8b6adf7c-f5fe-4473-b927-c90253d5f4cc",
        "id": "0b1ce496-c0c2-4c5c-92bc-cdb0472cb720",
        "shop_id": "c0554ffb-8e3a-4ce4-bb3b-d345873e061a",
        "sub_category": "2821a0ca-47f6-49d1-85fc-949e072cfbce"
    },
    {
        "featured_products": null,
        "isdeleted": false,
        "is_offer": null,
        "show_stock": true,
        "status": null,
        "top_selling": null,
        "trending_products": true,
        "discount": null,
        "duration": null,
        "expiry": null,
        "offered_price": 399,
        "price": 260,
        "quantity": null,
        "selling_price": 499,
        "stocks": 4,
        "attributes": null,
        "images": [
            "https://d246wdlhxeb44j.cloudfront.net/1741781046506-cropped-1741781046495.png"
        ],
        "alpha_numeric": null,
        "bar_code": null,
        "description": "<ul><li>cotton saree</li><li>summer special</li><li>offer</li></ul>",
        "image": null,
        "name": "cotton brown",
        "product_code": null,
        "videos": null,
        "created_at": "2025-03-12T12:04:13.924843",
        "updated_at": "2025-03-29T09:05:14.872368",
        "category": "8b6adf7c-f5fe-4473-b927-c90253d5f4cc",
        "id": "02877e90-4e17-4b43-beab-f0a988d80b70",
        "shop_id": "c0554ffb-8e3a-4ce4-bb3b-d345873e061a",
        "sub_category": "ab0965b3-1db4-49f2-85f0-bbd5121dd1ef"
    },
    {
        "featured_products": null,
        "isdeleted": false,
        "is_offer": null,
        "show_stock": true,
        "status": null,
        "top_selling": true,
        "trending_products": null,
        "discount": null,
        "duration": null,
        "expiry": null,
        "offered_price": null,
        "price": 650,
        "quantity": null,
        "selling_price": 899,
        "stocks": 7,
        "attributes": null,
        "images": [
            "https://d246wdlhxeb44j.cloudfront.net/1741507118798-cropped-1741507118788.png"
        ],
        "alpha_numeric": null,
        "bar_code": null,
        "description": "<ul><li>duel colour</li><li>work blouse combo</li><li>blouse point 90</li></ul>",
        "image": null,
        "name": "neenga asai patta saree",
        "product_code": null,
        "videos": null,
        "created_at": null,
        "updated_at": "2025-03-22T08:09:13.037677",
        "category": "8b6adf7c-f5fe-4473-b927-c90253d5f4cc",
        "id": "552b6e6f-6bf2-4751-85b7-f38c8bb57857",
        "shop_id": "c0554ffb-8e3a-4ce4-bb3b-d345873e061a",
        "sub_category": "5be3bab2-73ff-43a9-af87-e398a563c974"
    },
    {
        "featured_products": null,
        "isdeleted": false,
        "is_offer": null,
        "show_stock": true,
        "status": null,
        "top_selling": true,
        "trending_products": null,
        "discount": null,
        "duration": null,
        "expiry": null,
        "offered_price": 999,
        "price": 700,
        "quantity": null,
        "selling_price": 1049,
        "stocks": 7,
        "attributes": null,
        "images": [
            "https://d246wdlhxeb44j.cloudfront.net/1741871709920-cropped-1741871709909.png"
        ],
        "alpha_numeric": null,
        "bar_code": null,
        "description": "<ul><li>copper silk</li><li>border saree</li></ul>",
        "image": null,
        "name": "soft silk",
        "product_code": null,
        "videos": null,
        "created_at": "2025-03-13T13:15:16.13429",
        "updated_at": "2025-03-13T13:15:16.13429",
        "category": "8b6adf7c-f5fe-4473-b927-c90253d5f4cc",
        "id": "eec69b21-ed2f-4bdc-bb63-147b81075f44",
        "shop_id": "c0554ffb-8e3a-4ce4-bb3b-d345873e061a",
        "sub_category": "af8e85d8-3909-45fe-81a2-d3fb95260093"
    },
    {
        "featured_products": null,
        "isdeleted": false,
        "is_offer": null,
        "show_stock": true,
        "status": null,
        "top_selling": null,
        "trending_products": true,
        "discount": null,
        "duration": null,
        "expiry": null,
        "offered_price": 349,
        "price": 260,
        "quantity": null,
        "selling_price": 399,
        "stocks": 8,
        "attributes": null,
        "images": [
            "https://d246wdlhxeb44j.cloudfront.net/1741509826295-cropped-1741509826281.png"
        ],
        "alpha_numeric": null,
        "bar_code": null,
        "description": "<p>work blouse saree</p><p>blouse point 80</p><p>online</p>",
        "image": null,
        "name": "online",
        "product_code": null,
        "videos": null,
        "created_at": null,
        "updated_at": "2025-03-10T07:00:56.799272",
        "category": "8b6adf7c-f5fe-4473-b927-c90253d5f4cc",
        "id": "ec9f9f71-0a4c-48b1-a7ab-89577c80be41",
        "shop_id": "c0554ffb-8e3a-4ce4-bb3b-d345873e061a",
        "sub_category": "5be3bab2-73ff-43a9-af87-e398a563c974"
    },
    {
        "featured_products": null,
        "isdeleted": false,
        "is_offer": null,
        "show_stock": true,
        "status": null,
        "top_selling": null,
        "trending_products": true,
        "discount": null,
        "duration": null,
        "expiry": null,
        "offered_price": 349,
        "price": 260,
        "quantity": null,
        "selling_price": 399,
        "stocks": 6,
        "attributes": null,
        "images": [
            "https://d246wdlhxeb44j.cloudfront.net/1741508494202-cropped-1741508494181.png"
        ],
        "alpha_numeric": null,
        "bar_code": null,
        "description": "<ul><li>online trending</li><li>work blouse</li><li>combo</li></ul>",
        "image": null,
        "name": "online",
        "product_code": null,
        "videos": null,
        "created_at": null,
        "updated_at": "2025-03-15T10:57:44.353899",
        "category": "8b6adf7c-f5fe-4473-b927-c90253d5f4cc",
        "id": "fb38433d-fdf5-40b3-a9b3-93f4c5735f60",
        "shop_id": "c0554ffb-8e3a-4ce4-bb3b-d345873e061a",
        "sub_category": "5be3bab2-73ff-43a9-af87-e398a563c974"
    },
    {
        "featured_products": null,
        "isdeleted": false,
        "is_offer": null,
        "show_stock": true,
        "status": null,
        "top_selling": true,
        "trending_products": null,
        "discount": null,
        "duration": null,
        "expiry": null,
        "offered_price": null,
        "price": 650,
        "quantity": null,
        "selling_price": 899,
        "stocks": 11,
        "attributes": null,
        "images": [
            "https://d246wdlhxeb44j.cloudfront.net/1741509822319-cropped-1741509822309.png"
        ],
        "alpha_numeric": null,
        "bar_code": null,
        "description": "<ul><li>dual done</li><li>work blouse combo</li><li>blouse point 90</li></ul>",
        "image": null,
        "name": "neenga asai patta saree",
        "product_code": null,
        "videos": null,
        "created_at": null,
        "updated_at": "2025-03-28T15:03:58.829294",
        "category": "8b6adf7c-f5fe-4473-b927-c90253d5f4cc",
        "id": "c94e7595-21dd-494f-a824-4b5d48b42ccf",
        "shop_id": "c0554ffb-8e3a-4ce4-bb3b-d345873e061a",
        "sub_category": "5be3bab2-73ff-43a9-af87-e398a563c974"
    },
    {
        "featured_products": null,
        "isdeleted": false,
        "is_offer": null,
        "show_stock": true,
        "status": null,
        "top_selling": null,
        "trending_products": true,
        "discount": null,
        "duration": null,
        "expiry": null,
        "offered_price": 349,
        "price": 270,
        "quantity": null,
        "selling_price": 399,
        "stocks": 20,
        "attributes": null,
        "images": [
            "https://d246wdlhxeb44j.cloudfront.net/1741509476836-cropped-1741509476834.png"
        ],
        "alpha_numeric": null,
        "bar_code": null,
        "description": "<ul><li><strong><em>puspa 2 saree</em></strong></li><li><strong><em>running blouse</em></strong></li><li><strong><em>peacock pallu</em></strong></li></ul>",
        "image": null,
        "name": "puspa 2 saree",
        "product_code": null,
        "videos": null,
        "created_at": null,
        "updated_at": "2025-03-28T09:47:50.715723",
        "category": "8b6adf7c-f5fe-4473-b927-c90253d5f4cc",
        "id": "f76a8b7e-db8b-45fd-929f-46cbb5c70c87",
        "shop_id": "c0554ffb-8e3a-4ce4-bb3b-d345873e061a",
        "sub_category": "fcb3b625-c916-4119-ad88-e9555cc4f0a5"
    },
    {
        "featured_products": null,
        "isdeleted": false,
        "is_offer": null,
        "show_stock": true,
        "status": null,
        "top_selling": null,
        "trending_products": true,
        "discount": null,
        "duration": null,
        "expiry": null,
        "offered_price": 450,
        "price": 330,
        "quantity": null,
        "selling_price": 499,
        "stocks": 13,
        "attributes": null,
        "images": [
            "https://d246wdlhxeb44j.cloudfront.net/1741509504046-cropped-1741509504031.png"
        ],
        "alpha_numeric": null,
        "bar_code": null,
        "description": "<ul><li>brazzo</li><li>running blouse</li><li>super quality</li></ul>",
        "image": null,
        "name": "braze",
        "product_code": null,
        "videos": null,
        "created_at": null,
        "updated_at": "2025-03-17T06:38:56.118862",
        "category": "8b6adf7c-f5fe-4473-b927-c90253d5f4cc",
        "id": "81c92707-2eaf-45c9-aad7-0d1b70d71426",
        "shop_id": "c0554ffb-8e3a-4ce4-bb3b-d345873e061a",
        "sub_category": "a16e3941-94f7-4899-a2cf-dbacafd77f78"
    },
    {
        "featured_products": null,
        "isdeleted": false,
        "is_offer": null,
        "show_stock": true,
        "status": null,
        "top_selling": true,
        "trending_products": null,
        "discount": null,
        "duration": null,
        "expiry": null,
        "offered_price": 349,
        "price": 260,
        "quantity": null,
        "selling_price": 550,
        "stocks": 2,
        "attributes": null,
        "images": [
            "https://d246wdlhxeb44j.cloudfront.net/1741508011654-cropped-1741508011649.png"
        ],
        "alpha_numeric": null,
        "bar_code": null,
        "description": "<ul><li>Gemma offer</li><li>work blouse</li><li>ungalukaka</li></ul>",
        "image": null,
        "name": "offer for my followers",
        "product_code": null,
        "videos": null,
        "created_at": null,
        "updated_at": "2025-03-28T07:34:48.193766",
        "category": "8b6adf7c-f5fe-4473-b927-c90253d5f4cc",
        "id": "d440b8d4-5b63-46b5-a928-f3caea8799e7",
        "shop_id": "c0554ffb-8e3a-4ce4-bb3b-d345873e061a",
        "sub_category": "fcb3b625-c916-4119-ad88-e9555cc4f0a5"
    },
    {
        "featured_products": null,
        "isdeleted": false,
        "is_offer": null,
        "show_stock": true,
        "status": null,
        "top_selling": true,
        "trending_products": null,
        "discount": null,
        "duration": null,
        "expiry": null,
        "offered_price": null,
        "price": 650,
        "quantity": null,
        "selling_price": 899,
        "stocks": 9,
        "attributes": null,
        "images": [
            "https://d246wdlhxeb44j.cloudfront.net/1741507244287-cropped-1741507244277.png"
        ],
        "alpha_numeric": null,
        "bar_code": null,
        "description": "<ul><li>dual colour</li><li>work blouse combo</li><li>blouse point 90</li></ul>",
        "image": null,
        "name": "neenga asai patta saree",
        "product_code": null,
        "videos": null,
        "created_at": null,
        "updated_at": "2025-03-25T18:26:56.095402",
        "category": "8b6adf7c-f5fe-4473-b927-c90253d5f4cc",
        "id": "84a4e3b7-1417-496f-b939-b8f0197a28b3",
        "shop_id": "c0554ffb-8e3a-4ce4-bb3b-d345873e061a",
        "sub_category": "5be3bab2-73ff-43a9-af87-e398a563c974"
    },
    {
        "featured_products": null,
        "isdeleted": false,
        "is_offer": null,
        "show_stock": true,
        "status": null,
        "top_selling": null,
        "trending_products": true,
        "discount": null,
        "duration": null,
        "expiry": null,
        "offered_price": 449,
        "price": 360,
        "quantity": null,
        "selling_price": 499,
        "stocks": 3,
        "attributes": null,
        "images": [
            "https://d246wdlhxeb44j.cloudfront.net/1741508122371-cropped-1741508122359.png"
        ],
        "alpha_numeric": null,
        "bar_code": null,
        "description": "<ul><li>most sale sarees</li><li>work blouse </li><li>blouse point 90</li></ul>",
        "image": null,
        "name": "folwer velly",
        "product_code": null,
        "videos": null,
        "created_at": null,
        "updated_at": "2025-03-23T05:49:27.318468",
        "category": "8b6adf7c-f5fe-4473-b927-c90253d5f4cc",
        "id": "68383688-a4f6-4e16-a2f9-70b4cb33df65",
        "shop_id": "c0554ffb-8e3a-4ce4-bb3b-d345873e061a",
        "sub_category": "5be3bab2-73ff-43a9-af87-e398a563c974"
    },
    {
        "featured_products": null,
        "isdeleted": false,
        "is_offer": null,
        "show_stock": true,
        "status": null,
        "top_selling": null,
        "trending_products": true,
        "discount": null,
        "duration": null,
        "expiry": null,
        "offered_price": 449,
        "price": 330,
        "quantity": null,
        "selling_price": 499,
        "stocks": 7,
        "attributes": null,
        "images": [
            "https://d246wdlhxeb44j.cloudfront.net/1741509614076-cropped-1741509614061.png"
        ],
        "alpha_numeric": null,
        "bar_code": null,
        "description": "<ul><li>running blouse saress</li><li>braze</li></ul>",
        "image": null,
        "name": "braze",
        "product_code": null,
        "videos": null,
        "created_at": null,
        "updated_at": "2025-03-15T08:26:14.022914",
        "category": "8b6adf7c-f5fe-4473-b927-c90253d5f4cc",
        "id": "3560910f-3ea2-4350-a7b7-e8fadced8dbe",
        "shop_id": "c0554ffb-8e3a-4ce4-bb3b-d345873e061a",
        "sub_category": "a16e3941-94f7-4899-a2cf-dbacafd77f78"
    },
    {
        "featured_products": null,
        "isdeleted": false,
        "is_offer": null,
        "show_stock": false,
        "status": null,
        "top_selling": true,
        "trending_products": true,
        "discount": null,
        "duration": null,
        "expiry": null,
        "offered_price": null,
        "price": null,
        "quantity": null,
        "selling_price": null,
        "stocks": null,
        "attributes": [
            {
                "color": "Red",
                "price": "799",
                "images": [
                    "https://d246wdlhxeb44j.cloudfront.net/1742377862443-cropped-1742377862429.png"
                ],
                "stocks": "10",
                "offered_price": "720"
            },
            {
                "color": "Blue",
                "price": "799",
                "images": [
                    "https://d246wdlhxeb44j.cloudfront.net/1742377735186-cropped-1742377735172.png"
                ],
                "stocks": 9,
                "offered_price": "720"
            },
            {
                "color": "Pink",
                "price": "799",
                "images": [
                    "https://d246wdlhxeb44j.cloudfront.net/1742377924889-cropped-1742377924874.png"
                ],
                "stocks": "10",
                "offered_price": "720"
            },
            {
                "color": "Navy blue",
                "price": "799",
                "images": [
                    "https://d246wdlhxeb44j.cloudfront.net/1742377979022-cropped-1742377979007.png"
                ],
                "stocks": "10",
                "offered_price": "720"
            },
            {
                "color": "sky blue",
                "price": "799",
                "images": [
                    "https://d246wdlhxeb44j.cloudfront.net/1742378021232-cropped-1742378021217.png"
                ],
                "stocks": 8,
                "offered_price": "720"
            },
            {
                "color": "Brown",
                "price": "799",
                "images": [
                    "https://d246wdlhxeb44j.cloudfront.net/1742378060338-cropped-1742378060322.png"
                ],
                "stocks": "10",
                "offered_price": "720"
            },
            {
                "color": "violet",
                "price": "799",
                "images": [
                    "https://d246wdlhxeb44j.cloudfront.net/1742378124165-cropped-1742378124152.png"
                ],
                "stocks": "10",
                "offered_price": "720"
            },
            {
                "color": "rama green",
                "price": "799",
                "images": [
                    "https://d246wdlhxeb44j.cloudfront.net/1742378182886-cropped-1742378182873.png"
                ],
                "stocks": "10",
                "offered_price": "720"
            }
        ],
        "images": null,
        "alpha_numeric": null,
        "bar_code": null,
        "description": "<ul><li>STONE WORK</li><li>RUNNING BLOUSE</li><li>BLOUSE POINT 1 MET</li></ul>",
        "image": null,
        "name": "RAMZAN COLLECTIONS",
        "product_code": null,
        "videos": null,
        "created_at": "2025-03-19T09:55:48.013421",
        "updated_at": "2025-03-21T20:00:59.485983",
        "category": "8b6adf7c-f5fe-4473-b927-c90253d5f4cc",
        "id": "e0e68474-ee0a-4d31-a9f0-e83415d0e029",
        "shop_id": "c0554ffb-8e3a-4ce4-bb3b-d345873e061a",
        "sub_category": "2821a0ca-47f6-49d1-85fc-949e072cfbce"
    },
    {
        "featured_products": null,
        "isdeleted": false,
        "is_offer": null,
        "show_stock": false,
        "status": null,
        "top_selling": true,
        "trending_products": true,
        "discount": null,
        "duration": null,
        "expiry": null,
        "offered_price": null,
        "price": null,
        "quantity": null,
        "selling_price": null,
        "stocks": null,
        "attributes": [
            {
                "color": "Green",
                "price": "499",
                "images": [
                    "https://res.cloudinary.com/da9v7rkiv/image/upload/v1742813808/download_oj4te6.png"
                ],
                "stocks": 19,
                "offered_price": "399"
            },
            {
                "color": "Brown",
                "price": "499",
                "images": [
                    "https://res.cloudinary.com/da9v7rkiv/image/upload/v1742814525/download_i0akji.png"
                ],
                "stocks": 10,
                "offered_price": "399"
            }
        ],
        "images": null,
        "alpha_numeric": null,
        "bar_code": null,
        "description": "<ul><li>WORK BLOUSE COMBO</li><li>1000 PUTTA</li><li>BLOUSE POINT 90 POINT</li></ul>",
        "image": null,
        "name": "1000",
        "product_code": null,
        "videos": null,
        "created_at": "2025-03-23T13:04:54.999338",
        "updated_at": "2025-03-28T07:56:22.341104",
        "category": "8b6adf7c-f5fe-4473-b927-c90253d5f4cc",
        "id": "7e4d4b91-482e-4cd1-9856-fc5b1c16b2e8",
        "shop_id": "c0554ffb-8e3a-4ce4-bb3b-d345873e061a",
        "sub_category": "f276e563-294a-46fa-a8ef-19e40b4d3232"
    },
    {
        "featured_products": null,
        "isdeleted": false,
        "is_offer": null,
        "show_stock": false,
        "status": null,
        "top_selling": true,
        "trending_products": true,
        "discount": null,
        "duration": null,
        "expiry": null,
        "offered_price": null,
        "price": null,
        "quantity": null,
        "selling_price": null,
        "stocks": null,
        "attributes": [
            {
                "color": "Brown",
                "price": "1200",
                "images": [
                    "https://d246wdlhxeb44j.cloudfront.net/1742382144446-cropped-1742382144435.png"
                ],
                "stocks": 4,
                "offered_price": "999"
            },
            {
                "color": "Blue",
                "price": "1200",
                "images": [
                    "https://d246wdlhxeb44j.cloudfront.net/1742382199246-cropped-1742382199230.png"
                ],
                "stocks": 4,
                "offered_price": "999"
            },
            {
                "color": "rama green",
                "price": "1200",
                "images": [
                    "https://d246wdlhxeb44j.cloudfront.net/1742382283749-cropped-1742382283733.png"
                ],
                "stocks": "7",
                "offered_price": "999"
            },
            {
                "color": "violet",
                "price": "1200",
                "images": [
                    "https://d246wdlhxeb44j.cloudfront.net/1742382359268-cropped-1742382359253.png"
                ],
                "stocks": 4,
                "offered_price": "999"
            }
        ],
        "images": null,
        "alpha_numeric": null,
        "bar_code": null,
        "description": "<ul><li>Poonam cloth</li><li>stone work</li><li>running blouse</li></ul>",
        "image": null,
        "name": "semma collection",
        "product_code": null,
        "videos": null,
        "created_at": "2025-03-19T11:06:44.673858",
        "updated_at": "2025-03-23T00:35:53.267149",
        "category": "8b6adf7c-f5fe-4473-b927-c90253d5f4cc",
        "id": "a9d5feaa-09c8-4df3-8ccd-a4335a7faead",
        "shop_id": "c0554ffb-8e3a-4ce4-bb3b-d345873e061a",
        "sub_category": "2821a0ca-47f6-49d1-85fc-949e072cfbce"
    },
    {
        "featured_products": null,
        "isdeleted": false,
        "is_offer": null,
        "show_stock": true,
        "status": null,
        "top_selling": true,
        "trending_products": null,
        "discount": null,
        "duration": null,
        "expiry": null,
        "offered_price": null,
        "price": null,
        "quantity": null,
        "selling_price": null,
        "stocks": null,
        "attributes": [
            {
                "color": "BLUE",
                "price": "699",
                "images": [
                    "https://d246wdlhxeb44j.cloudfront.net/1741507551493-cropped-1741507551482.png"
                ],
                "stocks": 1,
                "offered_price": "649"
            },
            {
                "color": "PINK",
                "price": "699",
                "images": [
                    "https://d246wdlhxeb44j.cloudfront.net/1741507632576-cropped-1741507632566.png"
                ],
                "stocks": 0,
                "offered_price": "649"
            },
            {
                "color": "GREEN",
                "price": "699",
                "images": [
                    "https://d246wdlhxeb44j.cloudfront.net/1741507707200-cropped-1741507707188.png"
                ],
                "stocks": 0,
                "offered_price": "649"
            },
            {
                "color": "YELLOW",
                "price": "699",
                "images": [
                    "https://d246wdlhxeb44j.cloudfront.net/1741507777050-cropped-1741507777038.png"
                ],
                "stocks": 4,
                "offered_price": "649"
            },
            {
                "color": "ASH",
                "price": "699",
                "images": [
                    "https://d246wdlhxeb44j.cloudfront.net/1741507855767-cropped-1741507855756.png"
                ],
                "stocks": 3,
                "offered_price": "649"
            }
        ],
        "images": null,
        "alpha_numeric": null,
        "bar_code": null,
        "description": "<ul><li>net saree</li><li>wirk blouse combo</li><li>hip belt</li></ul>",
        "image": null,
        "name": "net saree ",
        "product_code": null,
        "videos": null,
        "created_at": null,
        "updated_at": "2025-03-20T12:23:52.644127",
        "category": "8b6adf7c-f5fe-4473-b927-c90253d5f4cc",
        "id": "9560da71-08c3-454d-acfe-56ddc6260a5a",
        "shop_id": "c0554ffb-8e3a-4ce4-bb3b-d345873e061a",
        "sub_category": "5be3bab2-73ff-43a9-af87-e398a563c974"
    },
    {
        "featured_products": null,
        "isdeleted": false,
        "is_offer": null,
        "show_stock": false,
        "status": null,
        "top_selling": true,
        "trending_products": true,
        "discount": null,
        "duration": null,
        "expiry": null,
        "offered_price": null,
        "price": null,
        "quantity": null,
        "selling_price": null,
        "stocks": null,
        "attributes": [
            {
                "color": "GREEN",
                "price": "799",
                "images": [
                    "https://d246wdlhxeb44j.cloudfront.net/1742039771760-cropped-1742039771748.png"
                ],
                "stocks": 0
            },
            {
                "color": "BLUE",
                "price": "799",
                "images": [
                    "https://d246wdlhxeb44j.cloudfront.net/1742039824437-cropped-1742039824423.png"
                ],
                "stocks": 3
            },
            {
                "color": "BROWN",
                "price": "799",
                "images": [
                    "https://d246wdlhxeb44j.cloudfront.net/1742039894446-cropped-1742039894435.png"
                ],
                "stocks": "5"
            },
            {
                "color": "NAVY BLUE",
                "price": "799",
                "images": [
                    "https://d246wdlhxeb44j.cloudfront.net/1742039950087-cropped-1742039950076.png"
                ],
                "stocks": 4
            },
            {
                "color": "BLACK",
                "price": "799",
                "images": [
                    "https://d246wdlhxeb44j.cloudfront.net/1742039986595-cropped-1742039986584.png"
                ],
                "stocks": 3
            }
        ],
        "images": null,
        "alpha_numeric": null,
        "bar_code": null,
        "description": "<ul><li>Poonam cloth</li><li>running blouse</li><li>stone work</li></ul>",
        "image": null,
        "name": "soft Poonam with stone",
        "product_code": null,
        "videos": null,
        "created_at": "2025-03-15T12:00:23.603392",
        "updated_at": "2025-03-21T06:06:47.515634",
        "category": "8b6adf7c-f5fe-4473-b927-c90253d5f4cc",
        "id": "b582a802-9be8-4491-920a-8d2613dc9b65",
        "shop_id": "c0554ffb-8e3a-4ce4-bb3b-d345873e061a",
        "sub_category": "2821a0ca-47f6-49d1-85fc-949e072cfbce"
    },
    {
        "featured_products": true,
        "isdeleted": true,
        "is_offer": null,
        "show_stock": false,
        "status": null,
        "top_selling": true,
        "trending_products": true,
        "discount": null,
        "duration": null,
        "expiry": null,
        "offered_price": null,
        "price": null,
        "quantity": null,
        "selling_price": null,
        "stocks": null,
        "attributes": [
            {
                "color": "Black",
                "price": "599",
                "images": [
                    "https://d246wdlhxeb44j.cloudfront.net/1742385943915-cropped-1742385943904.png"
                ],
                "stocks": 0
            },
            {
                "color": "Green",
                "price": "599",
                "images": [
                    "https://d246wdlhxeb44j.cloudfront.net/1742385974244-cropped-1742385974229.png"
                ],
                "stocks": 6
            },
            {
                "color": "Blue",
                "price": "599",
                "images": [
                    "https://d246wdlhxeb44j.cloudfront.net/1742386000639-cropped-1742386000624.png"
                ],
                "stocks": 0
            },
            {
                "color": "Brown",
                "price": "599",
                "images": [
                    "https://d246wdlhxeb44j.cloudfront.net/1742386050991-cropped-1742386050976.png"
                ],
                "stocks": 0
            }
        ],
        "images": null,
        "alpha_numeric": null,
        "bar_code": null,
        "description": "<ul><li>stone work running blouse</li><li>point 1 meter</li><li>cut work</li></ul>",
        "image": null,
        "name": "roja saree",
        "product_code": null,
        "videos": null,
        "created_at": "2025-03-19T12:07:56.571778",
        "updated_at": "2025-03-29T11:42:09.182778",
        "category": "8b6adf7c-f5fe-4473-b927-c90253d5f4cc",
        "id": "c5bbf19c-919b-483e-99c6-4d3848276dbf",
        "shop_id": "c0554ffb-8e3a-4ce4-bb3b-d345873e061a",
        "sub_category": "2821a0ca-47f6-49d1-85fc-949e072cfbce"
    },
    {
        "featured_products": null,
        "isdeleted": false,
        "is_offer": null,
        "show_stock": true,
        "status": null,
        "top_selling": true,
        "trending_products": true,
        "discount": null,
        "duration": null,
        "expiry": null,
        "offered_price": null,
        "price": null,
        "quantity": null,
        "selling_price": null,
        "stocks": null,
        "attributes": [
            {
                "color": "PINK",
                "price": "550",
                "images": [
                    "https://d246wdlhxeb44j.cloudfront.net/1742102343674-cropped-1742102343661.png"
                ],
                "stocks": 12
            },
            {
                "color": "lavender",
                "price": "550",
                "images": [
                    "https://d246wdlhxeb44j.cloudfront.net/1742102386111-cropped-1742102386096.png"
                ],
                "stocks": "8"
            },
            {
                "color": "peche",
                "price": "550",
                "images": [
                    "https://d246wdlhxeb44j.cloudfront.net/1742102412505-cropped-1742102412494.png"
                ],
                "stocks": 19
            },
            {
                "color": "rama green",
                "price": "550",
                "images": [
                    "https://d246wdlhxeb44j.cloudfront.net/1742102443893-cropped-1742102443880.png"
                ],
                "stocks": 11
            }
        ],
        "images": null,
        "alpha_numeric": null,
        "bar_code": null,
        "description": "<ul><li>hip belt</li><li>net blouse</li><li>satin cloth</li><li>blouse point 90</li></ul>",
        "image": null,
        "name": "hip belt saree",
        "product_code": null,
        "videos": null,
        "created_at": "2025-03-16T05:20:56.117708",
        "updated_at": "2025-03-25T09:02:37.476315",
        "category": "8b6adf7c-f5fe-4473-b927-c90253d5f4cc",
        "id": "b1ded68b-427d-4aaa-bddc-15797516eae2",
        "shop_id": "c0554ffb-8e3a-4ce4-bb3b-d345873e061a",
        "sub_category": "5be3bab2-73ff-43a9-af87-e398a563c974"
    },
    {
        "featured_products": null,
        "isdeleted": false,
        "is_offer": null,
        "show_stock": true,
        "status": null,
        "top_selling": true,
        "trending_products": true,
        "discount": null,
        "duration": null,
        "expiry": null,
        "offered_price": 130,
        "price": 80,
        "quantity": null,
        "selling_price": 300,
        "stocks": 8,
        "attributes": null,
        "images": [
            "https://d246wdlhxeb44j.cloudfront.net/1742223611263-cropped-1742223611250.png"
        ],
        "alpha_numeric": null,
        "bar_code": null,
        "description": "<ul><li>2 meter4 shall</li></ul>",
        "image": null,
        "name": "4 shall 130 random colours",
        "product_code": null,
        "videos": null,
        "created_at": "2025-03-17T15:02:14.084323",
        "updated_at": "2025-03-29T13:49:41.356341",
        "category": "8b6adf7c-f5fe-4473-b927-c90253d5f4cc",
        "id": "6d075d7e-3091-40cd-803f-55a176b49ebe",
        "shop_id": "c0554ffb-8e3a-4ce4-bb3b-d345873e061a",
        "sub_category": "ab0965b3-1db4-49f2-85f0-bbd5121dd1ef"
    },
    {
        "featured_products": null,
        "isdeleted": false,
        "is_offer": null,
        "show_stock": true,
        "status": null,
        "top_selling": null,
        "trending_products": null,
        "discount": null,
        "duration": null,
        "expiry": null,
        "offered_price": 999,
        "price": 780,
        "quantity": null,
        "selling_price": 1100,
        "stocks": 34,
        "attributes": null,
        "images": [
            "https://d246wdlhxeb44j.cloudfront.net/1742394780561-cropped-1742394780557.png",
            "https://d246wdlhxeb44j.cloudfront.net/1742394793356-cropped-1742394793351.png"
        ],
        "alpha_numeric": null,
        "bar_code": null,
        "description": "<p>Jyothika mam saree</p>",
        "image": null,
        "name": "Jyothika mam saree",
        "product_code": null,
        "videos": null,
        "created_at": "2025-03-19T14:33:19.823405",
        "updated_at": "2025-03-22T00:36:09.615837",
        "category": "8b6adf7c-f5fe-4473-b927-c90253d5f4cc",
        "id": "58ea6ff4-1f63-43e3-a715-845602bfc578",
        "shop_id": "c0554ffb-8e3a-4ce4-bb3b-d345873e061a",
        "sub_category": "af8e85d8-3909-45fe-81a2-d3fb95260093"
    },
    {
        "featured_products": null,
        "isdeleted": false,
        "is_offer": null,
        "show_stock": false,
        "status": null,
        "top_selling": true,
        "trending_products": true,
        "discount": null,
        "duration": null,
        "expiry": null,
        "offered_price": null,
        "price": null,
        "quantity": null,
        "selling_price": null,
        "stocks": null,
        "attributes": [
            {
                "color": "NAVY BLUE",
                "price": "2500",
                "images": [
                    "https://d246wdlhxeb44j.cloudfront.net/1742206493782-cropped-1742206493767.png"
                ],
                "stocks": "3",
                "offered_price": "999"
            },
            {
                "color": "PINK",
                "price": "2500",
                "images": [
                    "https://d246wdlhxeb44j.cloudfront.net/1742206538641-cropped-1742206538627.png"
                ],
                "stocks": 3,
                "offered_price": "999"
            },
            {
                "color": "rama green",
                "price": "2500",
                "images": [
                    "https://d246wdlhxeb44j.cloudfront.net/1742206748344-cropped-1742206748328.png"
                ],
                "stocks": 2,
                "offered_price": "999"
            },
            {
                "color": "dark green",
                "price": "2500",
                "images": [
                    "https://d246wdlhxeb44j.cloudfront.net/1742206810328-cropped-1742206810311.png"
                ],
                "stocks": "3",
                "offered_price": "999"
            },
            {
                "color": "PEACOCK GREEN",
                "price": "2500",
                "images": [
                    "https://d246wdlhxeb44j.cloudfront.net/1742206853393-cropped-1742206853377.png"
                ],
                "stocks": 0,
                "offered_price": "999"
            },
            {
                "color": "BLUE",
                "price": "2500",
                "images": [
                    "https://d246wdlhxeb44j.cloudfront.net/1742206929403-cropped-1742206929387.png"
                ],
                "stocks": 2,
                "offered_price": "999"
            }
        ],
        "images": null,
        "alpha_numeric": null,
        "bar_code": null,
        "description": "<ul><li>heavy work</li><li>semma quality</li></ul>",
        "image": null,
        "name": "full emberdary work saree",
        "product_code": null,
        "videos": null,
        "created_at": "2025-03-17T10:22:44.275621",
        "updated_at": "2025-03-22T10:10:43.737184",
        "category": "8b6adf7c-f5fe-4473-b927-c90253d5f4cc",
        "id": "406f2261-a1ab-44cd-a2ff-f41ffb958a09",
        "shop_id": "c0554ffb-8e3a-4ce4-bb3b-d345873e061a",
        "sub_category": "5be3bab2-73ff-43a9-af87-e398a563c974"
    },
    {
        "featured_products": null,
        "isdeleted": false,
        "is_offer": null,
        "show_stock": true,
        "status": null,
        "top_selling": true,
        "trending_products": true,
        "discount": null,
        "duration": null,
        "expiry": null,
        "offered_price": 999,
        "price": 690,
        "quantity": null,
        "selling_price": 1100,
        "stocks": 18,
        "attributes": null,
        "images": [
            "https://d246wdlhxeb44j.cloudfront.net/1742395430435-cropped-1742395430384.png"
        ],
        "alpha_numeric": null,
        "bar_code": null,
        "description": "<ul><li>ambani pattu</li></ul>",
        "image": null,
        "name": "Ambani pattu",
        "product_code": null,
        "videos": null,
        "created_at": "2025-03-19T14:44:35.487136",
        "updated_at": "2025-03-28T15:56:54.380708",
        "category": "8b6adf7c-f5fe-4473-b927-c90253d5f4cc",
        "id": "fe06a8df-530b-4df2-b1db-25b2cd2c9189",
        "shop_id": "c0554ffb-8e3a-4ce4-bb3b-d345873e061a",
        "sub_category": "af8e85d8-3909-45fe-81a2-d3fb95260093"
    },
    {
        "featured_products": null,
        "isdeleted": false,
        "is_offer": null,
        "show_stock": true,
        "status": null,
        "top_selling": true,
        "trending_products": true,
        "discount": null,
        "duration": null,
        "expiry": null,
        "offered_price": 1200,
        "price": 570,
        "quantity": null,
        "selling_price": 1500,
        "stocks": 9,
        "attributes": null,
        "images": [
            "https://d246wdlhxeb44j.cloudfront.net/1742233080837-cropped-1742233080821.png"
        ],
        "alpha_numeric": null,
        "bar_code": null,
        "description": "<ul><li>semma colour</li><li>work blouse</li><li>quality super</li></ul>",
        "image": null,
        "name": "rainbow colour saree",
        "product_code": null,
        "videos": null,
        "created_at": "2025-03-17T17:38:15.309718",
        "updated_at": "2025-03-17T17:38:15.309718",
        "category": "8b6adf7c-f5fe-4473-b927-c90253d5f4cc",
        "id": "97fc1be5-e4be-44e2-9bdd-7ee39348adbb",
        "shop_id": "c0554ffb-8e3a-4ce4-bb3b-d345873e061a",
        "sub_category": "5be3bab2-73ff-43a9-af87-e398a563c974"
    },
    {
        "featured_products": null,
        "isdeleted": false,
        "is_offer": null,
        "show_stock": false,
        "status": null,
        "top_selling": true,
        "trending_products": true,
        "discount": null,
        "duration": null,
        "expiry": null,
        "offered_price": null,
        "price": null,
        "quantity": null,
        "selling_price": null,
        "stocks": null,
        "attributes": [
            {
                "color": "Blue",
                "price": "499",
                "images": [
                    "https://res.cloudinary.com/dt9p4jpn3/image/upload/v1742708077/blue1_zpwuif.png"
                ],
                "stocks": 26,
                "offered_price": "449"
            },
            {
                "color": "Pink",
                "price": "499",
                "images": [
                    "https://res.cloudinary.com/dt9p4jpn3/image/upload/v1742708084/blue2_oavzny.png"
                ],
                "stocks": 7,
                "offered_price": "449"
            }
        ],
        "images": null,
        "alpha_numeric": null,
        "bar_code": null,
        "description": "<ul><li>STONE WORK</li><li>RUNNING BLOUSE</li><li>BLOUSE POINT 1 METE</li></ul>",
        "image": null,
        "name": "THAS102",
        "product_code": null,
        "videos": null,
        "created_at": "2025-03-22T14:41:28.873045",
        "updated_at": "2025-03-25T13:58:29.312439",
        "category": "8b6adf7c-f5fe-4473-b927-c90253d5f4cc",
        "id": "09c442e6-3d5a-4de0-8961-3e033584e01c",
        "shop_id": "c0554ffb-8e3a-4ce4-bb3b-d345873e061a",
        "sub_category": "2821a0ca-47f6-49d1-85fc-949e072cfbce"
    },
    {
        "featured_products": null,
        "isdeleted": false,
        "is_offer": null,
        "show_stock": false,
        "status": null,
        "top_selling": null,
        "trending_products": null,
        "discount": null,
        "duration": null,
        "expiry": null,
        "offered_price": null,
        "price": null,
        "quantity": null,
        "selling_price": null,
        "stocks": null,
        "attributes": [
            {
                "color": "BROWN",
                "price": "399",
                "images": [
                    "https://d246wdlhxeb44j.cloudfront.net/1741962995723-cropped-1741962995708.png"
                ],
                "stocks": 0
            },
            {
                "color": "YELLOW",
                "price": "399",
                "images": [
                    "https://d246wdlhxeb44j.cloudfront.net/1741963163674-cropped-1741963163658.png"
                ],
                "stocks": 4
            },
            {
                "color": "ASH",
                "price": "399",
                "images": [
                    "https://d246wdlhxeb44j.cloudfront.net/1741963229992-cropped-1741963229979.png"
                ],
                "stocks": "6"
            },
            {
                "color": "ORANGE",
                "price": "399",
                "images": [
                    "https://d246wdlhxeb44j.cloudfront.net/1741963370066-cropped-1741963370054.png"
                ],
                "stocks": "8"
            },
            {
                "color": "GREEN",
                "price": "399",
                "images": [
                    "https://d246wdlhxeb44j.cloudfront.net/1741963414364-cropped-1741963414353.png"
                ],
                "stocks": 4
            },
            {
                "color": "GREEN",
                "price": "399",
                "images": [
                    "https://d246wdlhxeb44j.cloudfront.net/1741963444744-cropped-1741963444730.png"
                ],
                "stocks": 4
            }
        ],
        "images": null,
        "alpha_numeric": null,
        "bar_code": null,
        "description": "<ul><li>work blouse combo</li><li>goog quilty</li><li>offer rate </li></ul>",
        "image": null,
        "name": "offer for you",
        "product_code": null,
        "videos": null,
        "created_at": "2025-03-14T14:46:46.064288",
        "updated_at": "2025-03-21T06:06:49.376354",
        "category": "8b6adf7c-f5fe-4473-b927-c90253d5f4cc",
        "id": "1fa71f4a-8915-4e5b-a6a3-288c1be8e1d6",
        "shop_id": "c0554ffb-8e3a-4ce4-bb3b-d345873e061a",
        "sub_category": "5be3bab2-73ff-43a9-af87-e398a563c974"
    },
    {
        "featured_products": null,
        "isdeleted": false,
        "is_offer": null,
        "show_stock": false,
        "status": null,
        "top_selling": true,
        "trending_products": true,
        "discount": null,
        "duration": null,
        "expiry": null,
        "offered_price": null,
        "price": null,
        "quantity": null,
        "selling_price": null,
        "stocks": null,
        "attributes": [
            {
                "color": "Yellow",
                "price": "420",
                "images": [
                    "https://d246wdlhxeb44j.cloudfront.net/1742398534008-cropped-1742398533986.png"
                ],
                "stocks": 10
            },
            {
                "color": "Green",
                "price": "420",
                "images": [
                    "https://d246wdlhxeb44j.cloudfront.net/1742398571141-cropped-1742398571118.png"
                ],
                "stocks": 20
            },
            {
                "color": "Orange",
                "price": "420",
                "images": [
                    "https://d246wdlhxeb44j.cloudfront.net/1742398599145-cropped-1742398599123.png"
                ],
                "stocks": 3
            },
            {
                "color": "Ash",
                "price": "420",
                "images": [
                    "https://d246wdlhxeb44j.cloudfront.net/1742398627914-cropped-1742398627891.png"
                ],
                "stocks": 19
            }
        ],
        "images": null,
        "alpha_numeric": null,
        "bar_code": null,
        "description": "<ul><li>work blouse</li><li>blouse point</li><li>90 point</li></ul><p><br></p>",
        "image": null,
        "name": "420 offer saree",
        "product_code": null,
        "videos": null,
        "created_at": "2025-03-19T15:37:16.532168",
        "updated_at": "2025-03-25T11:48:21.846381",
        "category": "8b6adf7c-f5fe-4473-b927-c90253d5f4cc",
        "id": "bb33bad2-fd02-42b3-8f22-fce25edef4e9",
        "shop_id": "c0554ffb-8e3a-4ce4-bb3b-d345873e061a",
        "sub_category": "5be3bab2-73ff-43a9-af87-e398a563c974"
    },
    {
        "featured_products": null,
        "isdeleted": false,
        "is_offer": null,
        "show_stock": false,
        "status": null,
        "top_selling": true,
        "trending_products": true,
        "discount": null,
        "duration": null,
        "expiry": null,
        "offered_price": null,
        "price": null,
        "quantity": null,
        "selling_price": null,
        "stocks": null,
        "attributes": [
            {
                "color": "lavender",
                "price": "850",
                "images": [
                    "https://d246wdlhxeb44j.cloudfront.net/1741953710091-cropped-1741953710086.png"
                ],
                "stocks": 4
            },
            {
                "color": "PINK",
                "price": "850",
                "images": [
                    "https://d246wdlhxeb44j.cloudfront.net/1741953740735-cropped-1741953740724.png"
                ],
                "stocks": "5"
            },
            {
                "color": "sky blue",
                "price": "850",
                "images": [
                    "https://d246wdlhxeb44j.cloudfront.net/1741953787049-cropped-1741953787039.png"
                ],
                "stocks": 4
            },
            {
                "color": "violet",
                "price": "850",
                "images": [
                    "https://d246wdlhxeb44j.cloudfront.net/1741953864647-cropped-1741953864636.png"
                ],
                "stocks": "5"
            }
        ],
        "images": null,
        "alpha_numeric": null,
        "bar_code": null,
        "description": "<ul><li>plain pattu</li><li>running blouse</li><li>with border</li><li><br></li></ul>",
        "image": null,
        "name": "fancy pattu",
        "product_code": null,
        "videos": null,
        "created_at": "2025-03-14T12:07:09.632572",
        "updated_at": "2025-03-20T01:52:00.080326",
        "category": "8b6adf7c-f5fe-4473-b927-c90253d5f4cc",
        "id": "4bb53640-8549-421d-812f-f57f81436c9c",
        "shop_id": "c0554ffb-8e3a-4ce4-bb3b-d345873e061a",
        "sub_category": "af8e85d8-3909-45fe-81a2-d3fb95260093"
    },
    {
        "featured_products": null,
        "isdeleted": false,
        "is_offer": null,
        "show_stock": false,
        "status": null,
        "top_selling": null,
        "trending_products": null,
        "discount": null,
        "duration": null,
        "expiry": null,
        "offered_price": null,
        "price": null,
        "quantity": null,
        "selling_price": null,
        "stocks": null,
        "attributes": [
            {
                "color": "YELLOW",
                "price": "499",
                "images": [
                    "https://d246wdlhxeb44j.cloudfront.net/1742142100026-cropped-1742142100015.png"
                ],
                "stocks": 7
            },
            {
                "color": "rama green",
                "price": "499",
                "images": [
                    "https://d246wdlhxeb44j.cloudfront.net/1742142143212-cropped-1742142143201.png"
                ],
                "stocks": "5"
            },
            {
                "color": "ORANGE",
                "price": "499",
                "images": [
                    "https://d246wdlhxeb44j.cloudfront.net/1742142171848-cropped-1742142171835.png"
                ],
                "stocks": 6
            },
            {
                "color": "GREEN",
                "price": "499",
                "images": [
                    "https://d246wdlhxeb44j.cloudfront.net/1742142231684-cropped-1742142231672.png"
                ],
                "stocks": 5
            },
            {
                "color": "peche",
                "price": "499",
                "images": [
                    "https://d246wdlhxeb44j.cloudfront.net/1742142259564-cropped-1742142259553.png"
                ],
                "stocks": 3
            },
            {
                "color": "dark green",
                "price": "499",
                "images": [
                    "https://d246wdlhxeb44j.cloudfront.net/1742188532444-cropped-1742188532429.png"
                ],
                "stocks": "7"
            }
        ],
        "images": null,
        "alpha_numeric": null,
        "bar_code": null,
        "description": "<ul><li>plain saree</li><li>work blouse</li><li>lays work border</li></ul>",
        "image": null,
        "name": "sunday mit nit sale",
        "product_code": null,
        "videos": null,
        "created_at": "2025-03-16T16:24:26.374417",
        "updated_at": "2025-03-21T05:53:38.002245",
        "category": "8b6adf7c-f5fe-4473-b927-c90253d5f4cc",
        "id": "fda88f3e-aac2-4d66-bc51-de3ffa45ecec",
        "shop_id": "c0554ffb-8e3a-4ce4-bb3b-d345873e061a",
        "sub_category": "5be3bab2-73ff-43a9-af87-e398a563c974"
    },
    {
        "featured_products": null,
        "isdeleted": false,
        "is_offer": null,
        "show_stock": true,
        "status": null,
        "top_selling": true,
        "trending_products": true,
        "discount": null,
        "duration": null,
        "expiry": null,
        "offered_price": null,
        "price": null,
        "quantity": null,
        "selling_price": null,
        "stocks": null,
        "attributes": [
            {
                "color": "PINK",
                "price": "435",
                "images": [
                    "https://d246wdlhxeb44j.cloudfront.net/1742125005986-cropped-1742125005958.png"
                ],
                "stocks": 0
            },
            {
                "color": "RED",
                "price": "435",
                "images": [
                    "https://d246wdlhxeb44j.cloudfront.net/1742125057825-cropped-1742125057810.png"
                ],
                "stocks": 0
            },
            {
                "color": "rama green",
                "price": "435",
                "images": [
                    "https://d246wdlhxeb44j.cloudfront.net/1742125096974-cropped-1742125096959.png"
                ],
                "stocks": 0
            },
            {
                "color": "BLUE",
                "price": "435",
                "images": [
                    "https://d246wdlhxeb44j.cloudfront.net/1742125132218-cropped-1742125132204.png"
                ],
                "stocks": 0
            },
            {
                "color": "violet",
                "price": "435",
                "images": [
                    "https://d246wdlhxeb44j.cloudfront.net/1742125171287-cropped-1742125171272.png"
                ],
                "stocks": 0
            },
            {
                "color": "GREEN",
                "price": "435",
                "images": [
                    "https://d246wdlhxeb44j.cloudfront.net/1742125217304-cropped-1742125217289.png"
                ],
                "stocks": 1
            }
        ],
        "images": null,
        "alpha_numeric": null,
        "bar_code": null,
        "description": "<p>stone work</p><p>putta design</p><p>running blouse</p>",
        "image": null,
        "name": "Sunday offer 2",
        "product_code": null,
        "videos": null,
        "created_at": "2025-03-16T11:40:36.355267",
        "updated_at": "2025-03-20T23:25:52.071569",
        "category": "8b6adf7c-f5fe-4473-b927-c90253d5f4cc",
        "id": "2851234a-c1f8-4d0c-9d1f-2d3f30110bee",
        "shop_id": "c0554ffb-8e3a-4ce4-bb3b-d345873e061a",
        "sub_category": "2821a0ca-47f6-49d1-85fc-949e072cfbce"
    },
    {
        "featured_products": null,
        "isdeleted": false,
        "is_offer": null,
        "show_stock": false,
        "status": null,
        "top_selling": true,
        "trending_products": true,
        "discount": null,
        "duration": null,
        "expiry": null,
        "offered_price": null,
        "price": null,
        "quantity": null,
        "selling_price": null,
        "stocks": null,
        "attributes": [
            {
                "color": "BLUE",
                "price": "2500",
                "images": [
                    "https://d246wdlhxeb44j.cloudfront.net/1742207429249-cropped-1742207429235.png"
                ],
                "stocks": 0,
                "offered_price": "999"
            },
            {
                "color": "BROWN",
                "price": "2500",
                "images": [
                    "https://d246wdlhxeb44j.cloudfront.net/1742207519570-cropped-1742207519552.png"
                ],
                "stocks": 0,
                "offered_price": "999"
            },
            {
                "color": "NAVY BLUE",
                "price": "2500",
                "images": [
                    "https://d246wdlhxeb44j.cloudfront.net/1742207645687-cropped-1742207645671.png"
                ],
                "stocks": 0,
                "offered_price": "999"
            },
            {
                "color": "sky blue",
                "price": "2500",
                "images": [
                    "https://d246wdlhxeb44j.cloudfront.net/1742207744417-cropped-1742207744399.png"
                ],
                "stocks": 1,
                "offered_price": "999"
            },
            {
                "color": "PINK",
                "price": "2500",
                "images": [
                    "https://d246wdlhxeb44j.cloudfront.net/1742207846527-cropped-1742207846512.png"
                ],
                "stocks": 6,
                "offered_price": "999"
            },
            {
                "color": "meron",
                "price": "2500",
                "images": [
                    "https://d246wdlhxeb44j.cloudfront.net/1742207963273-cropped-1742207963257.png"
                ],
                "stocks": "9",
                "offered_price": "999"
            }
        ],
        "images": null,
        "alpha_numeric": null,
        "bar_code": null,
        "description": "<ul><li>premium saree</li><li>Gemma quality</li></ul>",
        "image": null,
        "name": "embroidery work",
        "product_code": null,
        "videos": null,
        "created_at": "2025-03-17T10:38:07.36611",
        "updated_at": "2025-03-20T06:41:55.688536",
        "category": "8b6adf7c-f5fe-4473-b927-c90253d5f4cc",
        "id": "b09664f1-cb8f-4bd2-9f03-30fb466375aa",
        "shop_id": "c0554ffb-8e3a-4ce4-bb3b-d345873e061a",
        "sub_category": "5be3bab2-73ff-43a9-af87-e398a563c974"
    },
    {
        "featured_products": true,
        "isdeleted": false,
        "is_offer": null,
        "show_stock": false,
        "status": null,
        "top_selling": true,
        "trending_products": true,
        "discount": null,
        "duration": null,
        "expiry": null,
        "offered_price": null,
        "price": null,
        "quantity": null,
        "selling_price": null,
        "stocks": null,
        "attributes": [
            {
                "color": "Ash",
                "price": "549",
                "images": [
                    "https://res.cloudinary.com/dt9p4jpn3/image/upload/v1742485318/front1_nkbd6m.png"
                ],
                "stocks": 20
            },
            {
                "color": "Brown",
                "price": "549",
                "images": [
                    "https://res.cloudinary.com/dt9p4jpn3/image/upload/v1742485339/front3_hznizi.png"
                ],
                "stocks": 24
            },
            {
                "color": "Green",
                "price": "549",
                "images": [
                    "https://res.cloudinary.com/dt9p4jpn3/image/upload/v1742485330/front2_jfivrl.png"
                ],
                "stocks": 24
            },
            {
                "color": "Yellow",
                "price": "549",
                "images": [
                    "https://res.cloudinary.com/dt9p4jpn3/image/upload/v1742485361/front4_aivb0n.png"
                ],
                "stocks": 24
            }
        ],
        "images": null,
        "alpha_numeric": null,
        "bar_code": null,
        "description": "<ul><li>FANCY SAREE</li><li>RUNNING BLOUSE</li><li>STONE WORK</li></ul>",
        "image": null,
        "name": "THAS101",
        "product_code": null,
        "videos": null,
        "created_at": "2025-03-20T13:16:40.384152",
        "updated_at": "2025-03-25T10:43:27.742903",
        "category": "8b6adf7c-f5fe-4473-b927-c90253d5f4cc",
        "id": "29f4bb88-e1b1-4a9f-8fa6-0d45dec0baa9",
        "shop_id": "c0554ffb-8e3a-4ce4-bb3b-d345873e061a",
        "sub_category": "2821a0ca-47f6-49d1-85fc-949e072cfbce"
    },
    {
        "featured_products": null,
        "isdeleted": false,
        "is_offer": null,
        "show_stock": false,
        "status": null,
        "top_selling": true,
        "trending_products": true,
        "discount": null,
        "duration": null,
        "expiry": null,
        "offered_price": null,
        "price": null,
        "quantity": null,
        "selling_price": null,
        "stocks": null,
        "attributes": [
            {
                "color": "YELLOW",
                "price": "699",
                "images": [
                    "https://d246wdlhxeb44j.cloudfront.net/1742205639198-cropped-1742205639183.png"
                ],
                "stocks": 9
            },
            {
                "color": "PINK",
                "price": "699",
                "images": [
                    "https://d246wdlhxeb44j.cloudfront.net/1742205673176-cropped-1742205673161.png"
                ],
                "stocks": 9
            },
            {
                "color": "lavender",
                "price": "699",
                "images": [
                    "https://d246wdlhxeb44j.cloudfront.net/1742205710844-cropped-1742205710828.png"
                ],
                "stocks": 6
            },
            {
                "color": "sky blue",
                "price": "699",
                "images": [
                    "https://d246wdlhxeb44j.cloudfront.net/1742205750611-cropped-1742205750596.png"
                ],
                "stocks": 9
            },
            {
                "color": "rama green",
                "price": "699",
                "images": [
                    "https://d246wdlhxeb44j.cloudfront.net/1742205806910-cropped-1742205806896.png"
                ],
                "stocks": 9
            },
            {
                "color": "peche",
                "price": "699",
                "images": [
                    "https://d246wdlhxeb44j.cloudfront.net/1742205851438-cropped-1742205851423.png"
                ],
                "stocks": 8
            }
        ],
        "images": null,
        "alpha_numeric": null,
        "bar_code": null,
        "description": "<ul><li>party wear</li><li>stone work</li><li>running blouse</li><li>Fazal</li></ul>",
        "image": null,
        "name": "party wear saree",
        "product_code": null,
        "videos": null,
        "created_at": "2025-03-17T10:04:30.528367",
        "updated_at": "2025-03-21T07:22:06.167747",
        "category": "8b6adf7c-f5fe-4473-b927-c90253d5f4cc",
        "id": "4d9c6a6d-ef18-4dc8-a87e-0a3f777a164e",
        "shop_id": "c0554ffb-8e3a-4ce4-bb3b-d345873e061a",
        "sub_category": "2821a0ca-47f6-49d1-85fc-949e072cfbce"
    }
]